{"openapi":"3.0.1","info":{"title":"OpenAPI definition","version":"v0"},"servers":[{"url":"http://localhost:8080","description":"Generated server url"}],"paths":{"/api/users/{id}":{"get":{"tags":["user-controller"],"summary":"Get User by ID","description":"Retrieve a user by their unique identifier.","operationId":"getUserById","parameters":[{"name":"id","in":"path","required":true,"schema":{"type":"integer","format":"int64"}}],"responses":{"404":{"description":"User not found.","content":{"*/*":{"schema":{"$ref":"#/components/schemas/CustomApiResponseUserDto"}}}},"200":{"description":"Successfully retrieved the user.","content":{"*/*":{"schema":{"$ref":"#/components/schemas/CustomApiResponseUserDto"}}}}}},"put":{"tags":["user-controller"],"summary":"Update user","description":"Update the details of an existing user.","operationId":"updateUser","parameters":[{"name":"id","in":"path","required":true,"schema":{"type":"integer","format":"int64"}}],"requestBody":{"content":{"application/json":{"schema":{"$ref":"#/components/schemas/UserDto"}}},"required":true},"responses":{"200":{"description":"User updated successfully","content":{"*/*":{"schema":{"$ref":"#/components/schemas/CustomApiResponseUserDto"}}}},"404":{"description":"User not found","content":{"*/*":{"schema":{"$ref":"#/components/schemas/CustomApiResponseUserDto"}}}}}},"delete":{"tags":["user-controller"],"summary":"Delete User","description":"Delete a user by its ID.","operationId":"deleteUser","parameters":[{"name":"id","in":"path","required":true,"schema":{"type":"integer","format":"int64"}}],"responses":{"404":{"description":"User not found.","content":{"*/*":{"schema":{"$ref":"#/components/schemas/CustomApiResponseVoid"}}}},"204":{"description":"User deleted successfully.","content":{"*/*":{"schema":{"$ref":"#/components/schemas/CustomApiResponseVoid"}}}}}}},"/api/posts/{id}":{"get":{"tags":["post-controller"],"summary":"Get Post by ID","description":"Retrieve a post by their unique identifier.","operationId":"getPostById","parameters":[{"name":"id","in":"path","required":true,"schema":{"type":"integer","format":"int64"}}],"responses":{"200":{"description":"Successfully retrieved the post.","content":{"*/*":{"schema":{"$ref":"#/components/schemas/CustomApiResponsePostDto"}}}},"404":{"description":"Post not found.","content":{"*/*":{"schema":{"$ref":"#/components/schemas/CustomApiResponsePostDto"}}}}}},"put":{"tags":["post-controller"],"summary":"Update post","description":"Update the details of an existing post.","operationId":"updatePost","parameters":[{"name":"id","in":"path","required":true,"schema":{"type":"integer","format":"int64"}}],"requestBody":{"content":{"application/json":{"schema":{"$ref":"#/components/schemas/PostDto"}}},"required":true},"responses":{"404":{"description":"Post not found","content":{"*/*":{"schema":{"$ref":"#/components/schemas/CustomApiResponsePostDto"}}}},"200":{"description":"Post updated successfully","content":{"*/*":{"schema":{"$ref":"#/components/schemas/CustomApiResponsePostDto"}}}}}},"delete":{"tags":["post-controller"],"summary":"Delete Post","description":"Delete a post by its ID.","operationId":"deletePost","parameters":[{"name":"id","in":"path","required":true,"schema":{"type":"integer","format":"int64"}}],"responses":{"204":{"description":"Post deleted successfully.","content":{"*/*":{"schema":{"$ref":"#/components/schemas/CustomApiResponseVoid"}}}},"404":{"description":"Post not found.","content":{"*/*":{"schema":{"$ref":"#/components/schemas/CustomApiResponseVoid"}}}}}}},"/api/comments/{id}":{"get":{"tags":["comment-controller"],"summary":"Get Comment by ID","description":"Retrieve a user by their unique identifier.","operationId":"getCommentById","parameters":[{"name":"id","in":"path","required":true,"schema":{"type":"integer","format":"int64"}}],"responses":{"404":{"description":"Comment not found.","content":{"*/*":{"schema":{"$ref":"#/components/schemas/CustomApiResponseCommentDto"}}}},"200":{"description":"Successfully retrieved the comment.","content":{"*/*":{"schema":{"$ref":"#/components/schemas/CustomApiResponseCommentDto"}}}}}},"put":{"tags":["comment-controller"],"summary":"Update comment","description":"Update the details of an existing user.","operationId":"updateComment","parameters":[{"name":"id","in":"path","required":true,"schema":{"type":"integer","format":"int64"}}],"requestBody":{"content":{"application/json":{"schema":{"$ref":"#/components/schemas/CommentDto"}}},"required":true},"responses":{"200":{"description":"Comment updated successfully","content":{"*/*":{"schema":{"$ref":"#/components/schemas/CustomApiResponseCommentDto"}}}},"404":{"description":"Comment not found","content":{"*/*":{"schema":{"$ref":"#/components/schemas/CustomApiResponseCommentDto"}}}}}},"delete":{"tags":["comment-controller"],"summary":"Delete Comment","description":"Delete a comment by its ID.","operationId":"deleteComment","parameters":[{"name":"id","in":"path","required":true,"schema":{"type":"integer","format":"int64"}}],"responses":{"204":{"description":"Comment deleted successfully.","content":{"*/*":{"schema":{"$ref":"#/components/schemas/CustomApiResponseVoid"}}}},"404":{"description":"Comment not found.","content":{"*/*":{"schema":{"$ref":"#/components/schemas/CustomApiResponseVoid"}}}}}}},"/api/categories/{id}":{"get":{"tags":["category-controller"],"summary":"Get Category by ID","description":"Retrieve a category by their unique identifier.","operationId":"getCategoryById","parameters":[{"name":"id","in":"path","required":true,"schema":{"type":"integer","format":"int64"}}],"responses":{"404":{"description":"Category not found.","content":{"*/*":{"schema":{"$ref":"#/components/schemas/CustomApiResponseCategoryDto"}}}},"200":{"description":"Successfully retrieved the category.","content":{"*/*":{"schema":{"$ref":"#/components/schemas/CustomApiResponseCategoryDto"}}}}}},"put":{"tags":["category-controller"],"summary":"Update category","description":"Update the details of an existing category.","operationId":"updateCategory","parameters":[{"name":"id","in":"path","required":true,"schema":{"type":"integer","format":"int64"}}],"requestBody":{"content":{"application/json":{"schema":{"$ref":"#/components/schemas/CategoryDto"}}},"required":true},"responses":{"200":{"description":"Category updated successfully","content":{"*/*":{"schema":{"$ref":"#/components/schemas/CustomApiResponseCategoryDto"}}}},"404":{"description":"Category not found","content":{"*/*":{"schema":{"$ref":"#/components/schemas/CustomApiResponseCategoryDto"}}}}}},"delete":{"tags":["category-controller"],"summary":"Delete Category","description":"Delete a room by its ID.","operationId":"deleteCategory","parameters":[{"name":"id","in":"path","required":true,"schema":{"type":"integer","format":"int64"}}],"responses":{"204":{"description":"Category deleted successfully.","content":{"*/*":{"schema":{"$ref":"#/components/schemas/CustomApiResponseVoid"}}}},"404":{"description":"Category not found.","content":{"*/*":{"schema":{"$ref":"#/components/schemas/CustomApiResponseVoid"}}}}}}},"/api/users":{"get":{"tags":["user-controller"],"summary":"Get all Users with Pagination","description":"Retrieve a paginated list of all users.","operationId":"getAllUsers","parameters":[{"name":"page","in":"query","required":false,"schema":{"type":"integer","format":"int32","default":0}},{"name":"size","in":"query","required":false,"schema":{"type":"integer","format":"int32","default":10}}],"responses":{"200":{"description":"Successfully retrieved the list of users.","content":{"*/*":{"schema":{"$ref":"#/components/schemas/CustomApiResponsePageUserDto"}}}}}},"post":{"tags":["user-controller"],"summary":"Create a new User","description":"Create a new user record.","operationId":"createUser","requestBody":{"content":{"application/json":{"schema":{"$ref":"#/components/schemas/UserDto"}}},"required":true},"responses":{"201":{"description":"User created successfully.","content":{"*/*":{"schema":{"$ref":"#/components/schemas/CustomApiResponseUserDto"}}}}}}},"/api/posts":{"get":{"tags":["post-controller"],"summary":"Get all Posts with Pagination","description":"Retrieve a paginated list of all posts.","operationId":"getAllPosts","parameters":[{"name":"page","in":"query","required":false,"schema":{"type":"integer","format":"int32","default":0}},{"name":"size","in":"query","required":false,"schema":{"type":"integer","format":"int32","default":10}}],"responses":{"200":{"description":"Successfully retrieved the list of posts.","content":{"*/*":{"schema":{"$ref":"#/components/schemas/CustomApiResponsePagePostDto"}}}}}},"post":{"tags":["post-controller"],"summary":"Create a new Post","description":"Create a new post record.","operationId":"createPost","requestBody":{"content":{"application/json":{"schema":{"$ref":"#/components/schemas/PostDto"}}},"required":true},"responses":{"201":{"description":"Post created successfully.","content":{"*/*":{"schema":{"$ref":"#/components/schemas/CustomApiResponsePostDto"}}}}}}},"/api/comments/posts/{postId}":{"get":{"tags":["comment-controller"],"summary":"Get all Comments by Post ID","description":"Retrieve a list of all comments for specific post.","operationId":"getAllCommentsByPostId","parameters":[{"name":"postId","in":"path","required":true,"schema":{"type":"integer","format":"int64"}},{"name":"page","in":"query","required":false,"schema":{"type":"integer","format":"int32","default":0}},{"name":"size","in":"query","required":false,"schema":{"type":"integer","format":"int32","default":10}}],"responses":{"200":{"description":"Successfully retrieved the list of comments for specific post.","content":{"*/*":{"schema":{"$ref":"#/components/schemas/CustomApiResponsePageCommentDto"}}}}}},"post":{"tags":["comment-controller"],"summary":"Create a new Comment","description":"Create a new comment record for specific post.","operationId":"createComment","parameters":[{"name":"postId","in":"path","required":true,"schema":{"type":"integer","format":"int64"}}],"requestBody":{"content":{"application/json":{"schema":{"$ref":"#/components/schemas/CommentDto"}}},"required":true},"responses":{"201":{"description":"User created successfully.","content":{"*/*":{"schema":{"$ref":"#/components/schemas/CustomApiResponseCommentDto"}}}}}}},"/api/categories":{"get":{"tags":["category-controller"],"summary":"Get all Categories with Pagination","description":"Retrieve a paginated list of all categories.","operationId":"getAllCategories","parameters":[{"name":"page","in":"query","required":false,"schema":{"type":"integer","format":"int32","default":0}},{"name":"size","in":"query","required":false,"schema":{"type":"integer","format":"int32","default":10}}],"responses":{"200":{"description":"Successfully retrieved the list of categories.","content":{"*/*":{"schema":{"$ref":"#/components/schemas/CustomApiResponsePageCategoryDto"}}}}}},"post":{"tags":["category-controller"],"summary":"Create a new Category","description":"Create a new category record.","operationId":"createCategory","requestBody":{"content":{"application/json":{"schema":{"$ref":"#/components/schemas/CategoryDto"}}},"required":true},"responses":{"201":{"description":"Category created successfully.","content":{"*/*":{"schema":{"$ref":"#/components/schemas/CustomApiResponseCategoryDto"}}}}}}},"/api/posts/user/{userId}":{"get":{"tags":["post-controller"],"summary":"Get Posts by User with Pagination","description":"Retrieve a paginated list of posts by user ID.","operationId":"getPostsByUser","parameters":[{"name":"userId","in":"path","required":true,"schema":{"type":"integer","format":"int64"}},{"name":"page","in":"query","required":false,"schema":{"type":"integer","format":"int32","default":0}},{"name":"size","in":"query","required":false,"schema":{"type":"integer","format":"int32","default":10}}],"responses":{"200":{"description":"Successfully retrieved the list of posts by user.","content":{"*/*":{"schema":{"$ref":"#/components/schemas/CustomApiResponsePagePostDto"}}}}}}},"/api/posts/search":{"get":{"tags":["post-controller"],"summary":"Search Posts with Pagination","description":"Search posts by title or content with pagination.","operationId":"searchPosts","parameters":[{"name":"keyword","in":"query","required":true,"schema":{"type":"string"}},{"name":"page","in":"query","required":false,"schema":{"type":"integer","format":"int32","default":0}},{"name":"size","in":"query","required":false,"schema":{"type":"integer","format":"int32","default":10}}],"responses":{"200":{"description":"Successfully retrieved the list of posts based on the search keyword.","content":{"*/*":{"schema":{"$ref":"#/components/schemas/CustomApiResponsePagePostDto"}}}}}}},"/api/posts/category/{categoryId}":{"get":{"tags":["post-controller"],"summary":"Get Posts by Category with Pagination","description":"Retrieve a paginated list of posts by category ID.","operationId":"getPostsByCategory","parameters":[{"name":"categoryId","in":"path","required":true,"schema":{"type":"integer","format":"int64"}},{"name":"page","in":"query","required":false,"schema":{"type":"integer","format":"int32","default":0}},{"name":"size","in":"query","required":false,"schema":{"type":"integer","format":"int32","default":10}}],"responses":{"200":{"description":"Successfully retrieved the list of posts by category.","content":{"*/*":{"schema":{"$ref":"#/components/schemas/CustomApiResponsePagePostDto"}}}}}}},"/api/post/files/download/pdf/{postId}":{"get":{"tags":["post-download-controller"],"operationId":"downloadPDF","parameters":[{"name":"postId","in":"path","required":true,"schema":{"type":"integer","format":"int64"}}],"responses":{"200":{"description":"OK","content":{"*/*":{"schema":{"$ref":"#/components/schemas/CustomApiResponseVoid"}}}}}}},"/api/post/files/download/excel/{postId}":{"get":{"tags":["post-download-controller"],"operationId":"downloadExcel","parameters":[{"name":"postId","in":"path","required":true,"schema":{"type":"integer","format":"int64"}}],"responses":{"200":{"description":"OK","content":{"*/*":{"schema":{"$ref":"#/components/schemas/CustomApiResponseVoid"}}}}}}},"/api/post/files/download/csv/{postId}":{"get":{"tags":["post-download-controller"],"operationId":"downloadCSV","parameters":[{"name":"postId","in":"path","required":true,"schema":{"type":"integer","format":"int64"}}],"responses":{"200":{"description":"OK","content":{"*/*":{"schema":{"$ref":"#/components/schemas/CustomApiResponseVoid"}}}}}}}},"components":{"schemas":{"UserDto":{"required":["email","name","password"],"type":"object","properties":{"id":{"type":"integer","description":"Unique ID of the user","format":"int64","example":1},"name":{"type":"string","description":"Name of the user","example":"Nizomiddin Mirzanazarov"},"email":{"type":"string","description":"Email address of the user","example":"nizomiddinmirzanazarov@gmail.com"},"password":{"type":"string","description":"Password of the user","example":"password123"}},"description":"Data transfer object for User"},"CustomApiResponseUserDto":{"type":"object","properties":{"message":{"type":"string","description":"Message of the response"},"success":{"type":"boolean","description":"Indicates if the operation was successful"},"data":{"$ref":"#/components/schemas/UserDto"}},"description":"Response wrapper for API responses"},"PostDto":{"required":["content","title"],"type":"object","properties":{"id":{"type":"integer","description":"Unique ID of the post","format":"int64","example":1},"title":{"type":"string","description":"Title of the blog post","example":"Dependency Injection in Spring"},"content":{"type":"string","description":"Content of the blog post","example":"In this post, we will explore the concept of Dependency Injection..."},"image":{"type":"string","description":"Image associated with the blog post","example":"http://example.com/image.jpg"},"date":{"type":"string","description":"Date when the post was created","format":"date-time"},"categoryId":{"type":"integer","description":"Category ID for the post","format":"int64","example":3},"userId":{"type":"integer","description":"User ID for the post","format":"int64","example":7}},"description":"Data transfer object for Post"},"CustomApiResponsePostDto":{"type":"object","properties":{"message":{"type":"string","description":"Message of the response"},"success":{"type":"boolean","description":"Indicates if the operation was successful"},"data":{"$ref":"#/components/schemas/PostDto"}},"description":"Response wrapper for API responses"},"CommentDto":{"required":["content"],"type":"object","properties":{"id":{"type":"integer","description":"Unique ID of the comment","format":"int64","example":1},"content":{"type":"string","description":"Content of the comment made by the user","example":"This is a great post! I learned a lot from it."},"userId":{"type":"integer","description":"User ID made the comment","format":"int64","example":3},"postId":{"type":"integer","description":"Post ID for the comment","format":"int64","example":1}},"description":"Data transfer object for Comment"},"CustomApiResponseCommentDto":{"type":"object","properties":{"message":{"type":"string","description":"Message of the response"},"success":{"type":"boolean","description":"Indicates if the operation was successful"},"data":{"$ref":"#/components/schemas/CommentDto"}},"description":"Response wrapper for API responses"},"CategoryDto":{"type":"object","properties":{"id":{"type":"integer","description":"Unique ID of the category","format":"int64","example":1},"title":{"type":"string","description":"Title of the Category.","example":"Technology"},"description":{"type":"string","description":"A brief description of the Category.","example":"Posts related to technological advancements..."}},"description":"Data transfer object for Category"},"CustomApiResponseCategoryDto":{"type":"object","properties":{"message":{"type":"string","description":"Message of the response"},"success":{"type":"boolean","description":"Indicates if the operation was successful"},"data":{"$ref":"#/components/schemas/CategoryDto"}},"description":"Response wrapper for API responses"},"CustomApiResponsePageUserDto":{"type":"object","properties":{"message":{"type":"string","description":"Message of the response"},"success":{"type":"boolean","description":"Indicates if the operation was successful"},"data":{"$ref":"#/components/schemas/PageUserDto"}},"description":"Response wrapper for API responses"},"PageUserDto":{"type":"object","properties":{"totalElements":{"type":"integer","format":"int64"},"totalPages":{"type":"integer","format":"int32"},"size":{"type":"integer","format":"int32"},"content":{"type":"array","items":{"$ref":"#/components/schemas/UserDto"}},"number":{"type":"integer","format":"int32"},"sort":{"$ref":"#/components/schemas/SortObject"},"numberOfElements":{"type":"integer","format":"int32"},"first":{"type":"boolean"},"last":{"type":"boolean"},"pageable":{"$ref":"#/components/schemas/PageableObject"},"empty":{"type":"boolean"}}},"PageableObject":{"type":"object","properties":{"offset":{"type":"integer","format":"int64"},"sort":{"$ref":"#/components/schemas/SortObject"},"unpaged":{"type":"boolean"},"paged":{"type":"boolean"},"pageSize":{"type":"integer","format":"int32"},"pageNumber":{"type":"integer","format":"int32"}}},"SortObject":{"type":"object","properties":{"empty":{"type":"boolean"},"unsorted":{"type":"boolean"},"sorted":{"type":"boolean"}}},"CustomApiResponsePagePostDto":{"type":"object","properties":{"message":{"type":"string","description":"Message of the response"},"success":{"type":"boolean","description":"Indicates if the operation was successful"},"data":{"$ref":"#/components/schemas/PagePostDto"}},"description":"Response wrapper for API responses"},"PagePostDto":{"type":"object","properties":{"totalElements":{"type":"integer","format":"int64"},"totalPages":{"type":"integer","format":"int32"},"size":{"type":"integer","format":"int32"},"content":{"type":"array","items":{"$ref":"#/components/schemas/PostDto"}},"number":{"type":"integer","format":"int32"},"sort":{"$ref":"#/components/schemas/SortObject"},"numberOfElements":{"type":"integer","format":"int32"},"first":{"type":"boolean"},"last":{"type":"boolean"},"pageable":{"$ref":"#/components/schemas/PageableObject"},"empty":{"type":"boolean"}}},"CustomApiResponseVoid":{"type":"object","properties":{"message":{"type":"string","description":"Message of the response"},"success":{"type":"boolean","description":"Indicates if the operation was successful"},"data":{"type":"object"}},"description":"Response wrapper for API responses"},"CustomApiResponsePageCommentDto":{"type":"object","properties":{"message":{"type":"string","description":"Message of the response"},"success":{"type":"boolean","description":"Indicates if the operation was successful"},"data":{"$ref":"#/components/schemas/PageCommentDto"}},"description":"Response wrapper for API responses"},"PageCommentDto":{"type":"object","properties":{"totalElements":{"type":"integer","format":"int64"},"totalPages":{"type":"integer","format":"int32"},"size":{"type":"integer","format":"int32"},"content":{"type":"array","items":{"$ref":"#/components/schemas/CommentDto"}},"number":{"type":"integer","format":"int32"},"sort":{"$ref":"#/components/schemas/SortObject"},"numberOfElements":{"type":"integer","format":"int32"},"first":{"type":"boolean"},"last":{"type":"boolean"},"pageable":{"$ref":"#/components/schemas/PageableObject"},"empty":{"type":"boolean"}}},"CustomApiResponsePageCategoryDto":{"type":"object","properties":{"message":{"type":"string","description":"Message of the response"},"success":{"type":"boolean","description":"Indicates if the operation was successful"},"data":{"$ref":"#/components/schemas/PageCategoryDto"}},"description":"Response wrapper for API responses"},"PageCategoryDto":{"type":"object","properties":{"totalElements":{"type":"integer","format":"int64"},"totalPages":{"type":"integer","format":"int32"},"size":{"type":"integer","format":"int32"},"content":{"type":"array","items":{"$ref":"#/components/schemas/CategoryDto"}},"number":{"type":"integer","format":"int32"},"sort":{"$ref":"#/components/schemas/SortObject"},"numberOfElements":{"type":"integer","format":"int32"},"first":{"type":"boolean"},"last":{"type":"boolean"},"pageable":{"$ref":"#/components/schemas/PageableObject"},"empty":{"type":"boolean"}}}}}}